{
   "files": [ 

      
{
         "name": "TH-VIP-CAT-GAME-001",
         "url": "https://raw.githubusercontent.com/yeminhtet4541/htet/main/TH-VIP-001.ovpn"
      },


{
         "name": "TH-VIP-CAT-GAME-002",
         "url": "https://raw.githubusercontent.com/yeminhtet4541/htet/main/TH-VIP-002.ovpn"
      },


{
         "name": "TH-VIP-CAT-GAME-003",
         "url": "https://raw.githubusercontent.com/yeminhtet4541/htet/main/TH-VIP-CAT-GAME-003.ovpn"
      },


{
         "name": "TH-VIP-CAT-GAME-004",
         "url": "https://raw.githubusercontent.com/yeminhtet4541/htet/main/TH-VIP-CAT-GAME-004.ovpn"

      },




{
         "name": "TH-VIP-CAT-GAME-005",
         "url": "https://raw.githubusercontent.com/yeminhtet4541/htet/main/TH-VIP-CAT-GAME-005.ovpn"

      },



{
         "name": "TH-VIP-CAT-GAME-006",
         "url": "https://raw.githubusercontent.com/yeminhtet4541/htet/main/TH-VIP-006.ovpn"
      },



{
         "name": "TH-VIP-CAT-GAME-007",
         "url": "https://raw.githubusercontent.com/yeminhtet4541/htet/main/TH-VIP-CAT-GAME-007.ovpn"
      },


      
{
         "name": "TH-VIP-DTAC-008.ovpn",
         "url": "https://raw.githubusercontent.com/yeminhtet4541/htet/main/TH-VIP-DTAC-008.ovpn"
      },



      
{
         "name": "TH-VIP-TRUE-YT-009",
         "url": "https://raw.githubusercontent.com/yeminhtet4541/htet/main/TH-VIP-TRUE-YT-009.ovpn"
      }



   ],
"message":"3 Nov 2023\n\n•Version:27\n•50ဘတ်ကိုတစ်လ\n\n•Add DTAC NoFree\n\n•၀ယ်ယူအားပေးမှုအတွက်ကျေးဇူးပါ",
   "title":"ALl New VIP" ,
   "version": 27
}
